python_rako/__init__.py
python_rako/__version__.py
python_rako/bridge.py
python_rako/const.py
python_rako/exceptions.py
python_rako/helpers.py
python_rako/model.py
python_rako/py.typed
python_rako-0.0.14.dist-info/LICENSE
python_rako-0.0.14.dist-info/METADATA
python_rako-0.0.14.dist-info/WHEEL
python_rako-0.0.14.dist-info/top_level.txt
python_rako-0.0.14.dist-info/RECORD
