Metadata-Version: 2.1
Name: python-rako
Version: 0.0.14
Summary: Asynchronous Python client for Rako Controls Lighting.
Home-page: https://github.com/marengaz/python-rako
Author: Ben Marengo
Author-email: ben@marengo.co.uk
License: MIT
Keywords: rako,controls,api,async,client
Platform: any
Classifier: Intended Audience :: Developers
Classifier: License :: OSI Approved :: MIT License
Classifier: Operating System :: OS Independent
Classifier: Programming Language :: Python
Classifier: Programming Language :: Python :: 3
Classifier: Programming Language :: Python :: 3.8
Classifier: Programming Language :: Python :: 3.9
Classifier: Natural Language :: English
Classifier: Topic :: Software Development :: Libraries :: Python Modules
Classifier: Framework :: AsyncIO
Classifier: Development Status :: 4 - Beta
License-File: LICENSE
Requires-Dist: aiohttp
Requires-Dist: asyncio-dgram
Requires-Dist: xmltodict
